narmock/__init__.py
narmock/__main__.py
narmock/api.py
narmock/cli.py
narmock/generator.py
narmock/inspect.py
narmock/templates/__init__.py
narmock/templates/__mocks__.c.jinja2
narmock/templates/__mocks__.h.jinja2
narmock-0.2.17.dist-info/entry_points.txt
narmock-0.2.17.dist-info/LICENSE
narmock-0.2.17.dist-info/WHEEL
narmock-0.2.17.dist-info/METADATA
narmock-0.2.17.dist-info/RECORD
