Metadata-Version: 2.1
Name: narmock
Version: 0.2.17
Summary: A minimal mocking utility for C projects.
Home-page: https://github.com/vberlier/narmock
License: MIT
Keywords: c,mocking,tests,narwhal
Author: Valentin Berlier
Author-email: berlier.v@gmail.com
Requires-Python: >=3.7,<4.0
Classifier: License :: OSI Approved :: MIT License
Classifier: Programming Language :: Python :: 3
Classifier: Programming Language :: Python :: 3.10
Classifier: Programming Language :: Python :: 3.7
Classifier: Programming Language :: Python :: 3.8
Classifier: Programming Language :: Python :: 3.9
Requires-Dist: Jinja2 (>=3.0.3,<4.0.0)
Requires-Dist: pycparser (>=2.21,<3.0)
Project-URL: Documentation, https://github.com/vberlier/narmock
Project-URL: Repository, https://github.com/vberlier/narmock
